tzcity/__init__.py
tzcity/data.py
tzcity-0.0.3.dist-info/LICENSE
tzcity-0.0.3.dist-info/WHEEL
tzcity-0.0.3.dist-info/METADATA
tzcity-0.0.3.dist-info/RECORD
