Metadata-Version: 2.1
Name: tzcity
Version: 0.0.3
Summary: Module to translate city names to time zone names
Home-page: https://github.com/ju-sh/tzcity
License: UNKNOWN
Author: Julin S
Author-email: 
Requires-Python: >=3.6
Classifier: Programming Language :: Python :: 3
Classifier: Intended Audience :: Developers
Classifier: License :: OSI Approved :: MIT License
Classifier: Development Status :: 2 - Pre-Alpha
Classifier: Operating System :: OS Independent
Classifier: Topic :: Software Development :: Libraries :: Python Modules
Requires-Dist: mypy ; extra == "test"
Requires-Dist: flake8 ; extra == "test"
Requires-Dist: pylint ; extra == "test"
Requires-Dist: vulture ; extra == "test"
Requires-Dist: pytest ; extra == "test"
Requires-Dist: coverage ; extra == "test"
Requires-Dist: tox ; extra == "test"
Project-URL: Changelog, https://github.com/ju-sh/tzcity/blob/master/CHANGELOG.md
Project-URL: Issue Tracker, https://github.com/ju-sh/tzcity/issues
Provides-Extra: test
